ydk_models_cisco_ios_xr-6.4.1-nspkg.pth
ydk/models/cisco_ios_xr/Cisco_IOS_XR_Ethernet_SPAN_cfg.py
ydk/models/cisco_ios_xr/Cisco_IOS_XR_Ethernet_SPAN_datatypes.py
ydk/models/cisco_ios_xr/Cisco_IOS_XR_Ethernet_SPAN_oper.py
ydk/models/cisco_ios_xr/Cisco_IOS_XR_Ethernet_SPAN_subscriber_cfg.py
ydk/models/cisco_ios_xr/Cisco_IOS_XR_aaa_aaacore_cfg.py
ydk/models/cisco_ios_xr/Cisco_IOS_XR_aaa_diameter_oper.py
ydk/models/cisco_ios_xr/Cisco_IOS_XR_aaa_lib_cfg.py
ydk/models/cisco_ios_xr/Cisco_IOS_XR_aaa_lib_datatypes.py
ydk/models/cisco_ios_xr/Cisco_IOS_XR_aaa_locald_admin_cfg.py
ydk/models/cisco_ios_xr/Cisco_IOS_XR_aaa_locald_cfg.py
ydk/models/cisco_ios_xr/Cisco_IOS_XR_aaa_locald_oper.py
ydk/models/cisco_ios_xr/Cisco_IOS_XR_aaa_nacm_cfg.py
ydk/models/cisco_ios_xr/Cisco_IOS_XR_aaa_nacm_oper.py
ydk/models/cisco_ios_xr/Cisco_IOS_XR_aaa_protocol_radius_cfg.py
ydk/models/cisco_ios_xr/Cisco_IOS_XR_aaa_protocol_radius_oper.py
ydk/models/cisco_ios_xr/Cisco_IOS_XR_aaa_tacacs_cfg.py
ydk/models/cisco_ios_xr/Cisco_IOS_XR_accounting_cfg.py
ydk/models/cisco_ios_xr/Cisco_IOS_XR_alarmgr_server_oper.py
ydk/models/cisco_ios_xr/Cisco_IOS_XR_ascii_ltrace_oper.py
ydk/models/cisco_ios_xr/Cisco_IOS_XR_asic_errors_oper.py
ydk/models/cisco_ios_xr/Cisco_IOS_XR_asr9k_asic_errors_oper.py
ydk/models/cisco_ios_xr/Cisco_IOS_XR_asr9k_ext_usb_cfg.py
ydk/models/cisco_ios_xr/Cisco_IOS_XR_asr9k_fab_cfg.py
ydk/models/cisco_ios_xr/Cisco_IOS_XR_asr9k_fia_cfg.py
ydk/models/cisco_ios_xr/Cisco_IOS_XR_asr9k_fsi_oper.py
ydk/models/cisco_ios_xr/Cisco_IOS_XR_asr9k_lc_ethctrl_cfg.py
ydk/models/cisco_ios_xr/Cisco_IOS_XR_asr9k_lc_ethctrl_oper.py
ydk/models/cisco_ios_xr/Cisco_IOS_XR_asr9k_lc_fca_oper.py
ydk/models/cisco_ios_xr/Cisco_IOS_XR_asr9k_lc_pwrglide_cfg.py
ydk/models/cisco_ios_xr/Cisco_IOS_XR_asr9k_lpts_oper.py
ydk/models/cisco_ios_xr/Cisco_IOS_XR_asr9k_mlan_cmp_cfg.py
ydk/models/cisco_ios_xr/Cisco_IOS_XR_asr9k_netflow_oper.py
ydk/models/cisco_ios_xr/Cisco_IOS_XR_asr9k_np_oper.py
ydk_models_cisco_ios_xr-6.4.1.dist-info/DESCRIPTION.rst
ydk_models_cisco_ios_xr-6.4.1.dist-info/METADATA
ydk_models_cisco_ios_xr-6.4.1.dist-info/RECORD
ydk_models_cisco_ios_xr-6.4.1.dist-info/WHEEL
ydk_models_cisco_ios_xr-6.4.1.dist-info/metadata.json
ydk_models_cisco_ios_xr-6.4.1.dist-info/namespace_packages.txt
ydk_models_cisco_ios_xr-6.4.1.dist-info/top_level.txt
